bsm2_python/__init__.py
bsm2_python/_version.py
bsm2_python/bsm1_base.py
bsm2_python/bsm1_cl.py
bsm2_python/bsm1_ol.py
bsm2_python/bsm1_ps.py
bsm2_python/bsm2_base.py
bsm2_python/bsm2_cl.py
bsm2_python/bsm2_ol.py
bsm2_python/bsm2_olem.py
bsm2_python/bsm_base.py
bsm2_python/controller.py
bsm2_python/controller_em.py
bsm2_python/evaluation.py
bsm2_python/log.py
bsm2_python/simulation.py
bsm2_python/bsm2/__init__.py
bsm2_python/bsm2/adm1_bsm2.py
bsm2_python/bsm2/adm1_performance.py
bsm2_python/bsm2/aerationcontrol.py
bsm2_python/bsm2/asm1_bsm2.py
bsm2_python/bsm2/dewatering_bsm2.py
bsm2_python/bsm2/helpers_bsm2.py
bsm2_python/bsm2/module.py
bsm2_python/bsm2/plantperformance.py
bsm2_python/bsm2/primclar_bsm2.py
bsm2_python/bsm2/settler1d_bsm2.py
bsm2_python/bsm2/storage_bsm2.py
bsm2_python/bsm2/thickener_bsm2.py
bsm2_python/bsm2/init/__init__.py
bsm2_python/bsm2/init/adm1init_bsm2.py
bsm2_python/bsm2/init/aerationcontrolinit.py
bsm2_python/bsm2/init/aerationcontrolinit_bsm1.py
bsm2_python/bsm2/init/asm1init_bsm1.py
bsm2_python/bsm2/init/asm1init_bsm2.py
bsm2_python/bsm2/init/dewateringinit_bsm2.py
bsm2_python/bsm2/init/plantperformanceinit_bsm1.py
bsm2_python/bsm2/init/plantperformanceinit_bsm2.py
bsm2_python/bsm2/init/primclarinit_bsm2.py
bsm2_python/bsm2/init/reginit_bsm1.py
bsm2_python/bsm2/init/reginit_bsm2.py
bsm2_python/bsm2/init/settler1dinit_bsm2.py
bsm2_python/bsm2/init/storageinit_bsm2.py
bsm2_python/bsm2/init/thickenerinit_bsm2.py
bsm2_python/data/asm1_aerationvalues_ss_ps.csv
bsm2_python/data/asm1_values_ss_ps.csv
bsm2_python/data/bsm2_values_ss.csv
bsm2_python/data/constinfluent_bsm2.csv
bsm2_python/data/dryinfluent.csv
bsm2_python/data/dyninfluent_bsm2.csv
bsm2_python/data/dynsludge_bsm2.csv
bsm2_python/data/electricity_prices_2023.csv
bsm2_python/data/evaluation_ss.csv
bsm2_python/data/raininfluent.csv
bsm2_python/data/sensornoise.csv
bsm2_python/energy_management/__init__.py
bsm2_python/energy_management/boiler.py
bsm2_python/energy_management/chp.py
bsm2_python-0.0.16.dist-info/METADATA
bsm2_python-0.0.16.dist-info/WHEEL
bsm2_python-0.0.16.dist-info/licenses/AUTHORS.md
bsm2_python-0.0.16.dist-info/licenses/LICENSE
bsm2_python-0.0.16.dist-info/RECORD
