Metadata-Version: 2.4
Name: bsm2-python
Version: 0.0.16
Summary: A Python implementation of the Benchmark Simulation Model 2 (BSM2) plant layout according to the IWA standard.
Project-URL: Documentation, https://bsm2-python.readthedocs.io/
Project-URL: Source, https://github.com/FAU-EVT/bsm2-python
Author-email: Jonas Miederer <jonas.miederer@fau.de>
License: BSD-3-Clause
License-File: AUTHORS.md
License-File: LICENSE
Keywords: benchmark simulation model 2,bsm2,simulation,system dynamics,wastewater treatment plant
Classifier: Development Status :: 4 - Beta
Classifier: Framework :: Hatch
Classifier: Intended Audience :: Education
Classifier: Intended Audience :: Science/Research
Classifier: License :: OSI Approved :: BSD License
Classifier: Natural Language :: English
Classifier: Operating System :: OS Independent
Classifier: Programming Language :: Python
Classifier: Programming Language :: Python :: 3.10
Classifier: Programming Language :: Python :: 3.11
Classifier: Programming Language :: Python :: 3.12
Classifier: Programming Language :: Python :: Implementation :: CPython
Classifier: Topic :: Scientific/Engineering
Classifier: Topic :: Scientific/Engineering :: Hydrology
Requires-Python: >=3.10
Requires-Dist: control
Requires-Dist: matplotlib
Requires-Dist: numba
Requires-Dist: numpy
Requires-Dist: scipy
Requires-Dist: tqdm
